{
    "createdById": "005xx000001XJuXAAW",
    "createdDate": "2021-07-20T12:50:07.000+0000",
    "definitionId": "300xx000000cENNAA2",
    "fieldsToNull": [],
    "fullName": "RecordTriggeredFlow",
    "id": "301xx000003Gy4lAAC",
    "lastModifiedBy": {
        "fieldsToNull": [],
        "name": "User User"
    },
    "lastModifiedById": "005xx000001XJuXAAW",
    "lastModifiedDate": "2021-07-20T12:50:11.000+0000",
    "manageableState": "unmanaged",
    "masterLabel": "RecordTriggeredFlow",
    "metadata": {
        "actionCalls": [
            {
                "actionName": "chatterPost",
                "actionType": "chatterPost",
                "dataTypeMappings": [],
                "flowTransactionModel": "CurrentTransaction",
                "inputParameters": [
                    {
                        "name": "text",
                        "processMetadataValues": [],
                        "value": {
                            "stringValue": "Foo"
                        }
                    },
                    {
                        "name": "subjectNameOrId",
                        "processMetadataValues": [],
                        "value": {
                            "stringValue": "Bar"
                        }
                    },
                    {
                        "name": "type",
                        "processMetadataValues": [],
                        "value": {
                            "stringValue": ""
                        }
                    },
                    {
                        "name": "visibility",
                        "processMetadataValues": [],
                        "value": {
                            "elementReference": "accountSObjectVariable.Owner.IsActive"
                        }
                    }
                ],
                "label": "Post to Chatter Action",
                "locationX": 578,
                "locationY": 528,
                "name": "Post_to_Chatter_Action",
                "outputParameters": [],
                "processMetadataValues": [],
                "storeOutputAutomatically": false
            }
        ],
        "apexPluginCalls": [],
        "apiVersion": 51,
        "assignments": [
            {
                "assignmentItems": [
                    {
                        "assignToReference": "$Record.Description",
                        "operator": "Add",
                        "processMetadataValues": [],
                        "value": {
                            "elementReference": "$Record__Prior.AnnualRevenue"
                        }
                    }
                ],
                "label": "assign",
                "locationX": 380,
                "locationY": 1103,
                "name": "assign",
                "processMetadataValues": []
            }
        ],
        "choices": [],
        "collectionProcessors": [],
        "constants": [],
        "decisions": [
            {
                "defaultConnectorLabel": "Default Outcome",
                "label": "decision",
                "locationX": 710,
                "locationY": 408,
                "name": "decision",
                "processMetadataValues": [],
                "rules": [
                    {
                        "conditionLogic": "and",
                        "conditions": [
                            {
                                "leftValueReference": "$Record__Prior.Name",
                                "operator": "EqualTo",
                                "processMetadataValues": [],
                                "rightValue": {
                                    "stringValue": "theAccount"
                                }
                            }
                        ],
                        "connector": {
                            "isGoTo": false,
                            "processMetadataValues": [],
                            "targetReference": "Post_to_Chatter_Action"
                        },
                        "doesRequireRecordChangedToMeetCriteria": false,
                        "label": "outcome",
                        "name": "outcome",
                        "processMetadataValues": []
                    }
                ]
            }
        ],
        "dynamicChoiceSets": [],
        "environments": ["Default"],
        "formulas": [],
        "interviewLabel": "RecordTriggeredFlow {!$Flow.CurrentDateTime}",
        "isAdditionalPermissionRequiredToRun": false,
        "isOverridable": false,
        "isTemplate": false,
        "label": "RecordTriggeredFlow",
        "loops": [],
        "orchestratedStages": [],
        "processMetadataValues": [
            {
                "name": "BuilderType",
                "value": {
                    "stringValue": "LightningFlowBuilder"
                }
            },
            {
                "name": "CanvasMode",
                "value": {
                    "stringValue": "AUTO_LAYOUT_CANVAS"
                }
            },
            {
                "name": "OriginBuilderType",
                "value": {
                    "stringValue": "LightningFlowBuilder"
                }
            }
        ],
        "processType": "AutoLaunchedFlow",
        "recordCreates": [
            {
                "connector": {
                    "isGoTo": false,
                    "processMetadataValues": [],
                    "targetReference": "updateTriggerRecordWithRelatedFields"
                },
                "inputAssignments": [],
                "inputReference": "accountSObjectVariable",
                "label": "create account from an account",
                "locationX": 50,
                "locationY": 288,
                "name": "create_account_from_an_account",
                "processMetadataValues": [],
                "storeOutputAutomatically": false
            },
            {
                "assignRecordIdToReference": "stringVariable",
                "connector": {
                    "isGoTo": false,
                    "processMetadataValues": [],
                    "targetReference": "updateTriggerRecordWithRelatedFields"
                },
                "inputAssignments": [
                    {
                        "field": "Name",
                        "processMetadataValues": [],
                        "value": {
                            "stringValue": "accountName"
                        }
                    }
                ],
                "label": "create account manual output",
                "locationX": 314,
                "locationY": 288,
                "name": "create_account_manual_output",
                "object": "Account",
                "processMetadataValues": [],
                "storeOutputAutomatically": false
            }
        ],
        "recordDeletes": [],
        "recordLookups": [],
        "recordRollbacks": [],
        "recordUpdates": [
            {
                "connector": {
                    "isGoTo": false,
                    "processMetadataValues": [],
                    "targetReference": "decision"
                },
                "filters": [],
                "inputAssignments": [
                    {
                        "field": "Name",
                        "processMetadataValues": [],
                        "value": {
                            "stringValue": "Trigg"
                        }
                    }
                ],
                "inputReference": "$Record",
                "label": "Update Triggering Record",
                "locationX": 710,
                "locationY": 288,
                "name": "Update_Triggering_Record",
                "processMetadataValues": []
            },
            {
                "connector": {
                    "isGoTo": false,
                    "processMetadataValues": [],
                    "targetReference": "assign"
                },
                "description": "$Record is an Account and the related entity is Assets\nThere is only 1 filter, and 1 assignment.\nThe assignment is the price.",
                "filterLogic": "and",
                "filters": [
                    {
                        "field": "MailingCity",
                        "operator": "EqualTo",
                        "processMetadataValues": [],
                        "value": {
                            "elementReference": "$Record.BillingCity"
                        }
                    }
                ],
                "inputAssignments": [
                    {
                        "field": "Description",
                        "processMetadataValues": [],
                        "value": {
                            "elementReference": "$User.Signature"
                        }
                    }
                ],
                "inputReference": "$Record.Parent.Contacts",
                "label": "updateTriggerRecordWithRelatedFields",
                "locationX": 380,
                "locationY": 983,
                "name": "updateTriggerRecordWithRelatedFields",
                "processMetadataValues": []
            }
        ],
        "screens": [],
        "stages": [],
        "start": {
            "connector": {
                "isGoTo": false,
                "processMetadataValues": [],
                "targetReference": "create_account_from_an_account"
            },
            "doesRequireRecordChangedToMeetCriteria": true,
            "filterLogic": "and",
            "filters": [
                {
                    "field": "BillingCity",
                    "operator": "EqualTo",
                    "processMetadataValues": [],
                    "value": {
                        "stringValue": "San Francisco"
                    }
                }
            ],
            "locationX": 254,
            "locationY": 0,
            "object": "Account",
            "processMetadataValues": [],
            "recordTriggerType": "Update",
            "scheduledPaths": [
                {
                    "connector": {
                        "isGoTo": false,
                        "processMetadataValues": [],
                        "targetReference": "create_account_manual_output"
                    },
                    "label": "myScheduledPath2DaysBefore",
                    "maxBatchSize": 0,
                    "name": "myScheduledPath2DaysBefore",
                    "offsetNumber": -2,
                    "offsetUnit": "Days",
                    "processMetadataValues": [],
                    "recordField": "CreatedDate",
                    "timeSource": "RecordField"
                },
                {
                    "connector": {
                        "isGoTo": false,
                        "processMetadataValues": [],
                        "targetReference": "Update_Triggering_Record"
                    },
                    "label": "myScheduledPathHoursAfter",
                    "maxBatchSize": 0,
                    "name": "myScheduledPathHoursAfter",
                    "offsetNumber": 4,
                    "offsetUnit": "Hours",
                    "processMetadataValues": [],
                    "recordField": "LastModifiedDate",
                    "timeSource": "RecordField"
                }
            ],
            "triggerType": "RecordAfterSave"
        },
        "status": "InvalidDraft",
        "steps": [],
        "subflows": [],
        "textTemplates": [],
        "variables": [
            {
                "dataType": "SObject",
                "isCollection": false,
                "isInput": false,
                "isOutput": false,
                "name": "accountSObjectVariable",
                "objectType": "Account",
                "processMetadataValues": [],
                "scale": 0
            },
            {
                "dataType": "String",
                "isCollection": false,
                "isInput": false,
                "isOutput": false,
                "name": "stringVariable",
                "processMetadataValues": [],
                "scale": 0
            }
        ],
        "waits": []
    },
    "processType": "AutoLaunchedFlow",
    "status": "InvalidDraft",
    "versionNumber": 1
}
